sx1509_gpio_expander/IO_Types.py
sx1509_gpio_expander/SX1509.py
sx1509_gpio_expander/__init__.py
sx1509_gpio_expander-0.1.2.dist-info/METADATA
sx1509_gpio_expander-0.1.2.dist-info/WHEEL
sx1509_gpio_expander-0.1.2.dist-info/licenses/LICENSE
sx1509_gpio_expander-0.1.2.dist-info/RECORD
