Metadata-Version: 2.3
Name: sx1509_gpio_expander
Version: 0.1.2
Summary: A package to control the SX1509 GPIO expander
Project-URL: Homepage, https://github.com/T-N-S/SX1509_gpio_expander_package
Author-email: Tim Schumann <gerb008701@gmail.com>
License-File: LICENSE
